{"is_source_file": true, "format": "JavaScript", "description": "This is a React component source file that implements a Snake game with custom graphics, controls, and game logic.", "external_files": ["./App.css"], "external_methods": ["getComputedStyle", "window.addEventListener", "window.removeEventListener", "setInterval", "clearInterval", "Math.random", "Math.floor"], "published": ["default"], "classes": [], "methods": [{"name": "getRandomTreasure(snake)", "description": "Generates a random grid position for the treasure, avoiding positions occupied by the snake.", "scope": "", "scopeKind": ""}, {"name": "roundRect(ctx, x, y, w, h, r)", "description": "Draws a rounded rectangle on the canvas.", "scope": "", "scopeKind": ""}, {"name": "drawDiamond(ctx, cx, cy, size)", "description": "Draws a diamond-shaped treasure with a gradient and highlight.", "scope": "", "scopeKind": ""}, {"name": "App()", "scope": "", "scopeKind": "", "description": "unavailable"}, {"name": "updateCanvasScale()", "scope": "App", "scopeKind": "function", "description": "unavailable"}], "calls": ["setInterval", "clearInterval", "getComputedStyle", "document.documentElement.getPropertyValue", "Math.random", "Math.floor"], "search-terms": ["React component", "Snake game", "canvas rendering", "game controls", "treasure gem", "responsive canvas", "game loop"], "state": 2, "file_id": 6, "knowledge_revision": 26, "git_revision": "b70ce28a398d24e2d66f63667dc3170b4c5ee801", "revision_history": [{"24": "b70ce28a398d24e2d66f63667dc3170b4c5ee801"}, {"26": "b70ce28a398d24e2d66f63667dc3170b4c5ee801"}], "ctags": [{"_type": "tag", "name": "App", "path": "/home/kavia/workspace/code-generation/treasure-snake-game-1417-1426/snake_game_frontend/src/App.js", "pattern": "/^export default function App() {$/", "language": "JavaScript", "kind": "function", "signature": "()"}, {"_type": "tag", "name": "CELL_SIZE", "path": "/home/kavia/workspace/code-generation/treasure-snake-game-1417-1426/snake_game_frontend/src/App.js", "pattern": "/^const CELL_SIZE = 24; \\/\\/ pixels per cell (canvas size adjusts responsively)$/", "language": "JavaScript", "kind": "constant"}, {"_type": "tag", "name": "GRID_SIZE", "path": "/home/kavia/workspace/code-generation/treasure-snake-game-1417-1426/snake_game_frontend/src/App.js", "pattern": "/^              height={GRID_SIZE * CELL_SIZE}$/", "language": "JavaScript", "kind": "field", "scope": "App.height", "scopeKind": "class"}, {"_type": "tag", "name": "GRID_SIZE", "path": "/home/kavia/workspace/code-generation/treasure-snake-game-1417-1426/snake_game_frontend/src/App.js", "pattern": "/^              width={GRID_SIZE * CELL_SIZE}$/", "language": "JavaScript", "kind": "field", "scope": "App.width", "scopeKind": "class"}, {"_type": "tag", "name": "GRID_SIZE", "path": "/home/kavia/workspace/code-generation/treasure-snake-game-1417-1426/snake_game_frontend/src/App.js", "pattern": "/^const GRID_SIZE = 20; \\/\\/ number of cells in each dimension$/", "language": "JavaScript", "kind": "constant"}, {"_type": "tag", "name": "INITIAL_DIRECTION", "path": "/home/kavia/workspace/code-generation/treasure-snake-game-1417-1426/snake_game_frontend/src/App.js", "pattern": "/^const INITIAL_DIRECTION = { x: 1, y: 0 }; \\/\\/ moving right$/", "language": "JavaScript", "kind": "class"}, {"_type": "tag", "name": "INITIAL_SNAKE", "path": "/home/kavia/workspace/code-generation/treasure-snake-game-1417-1426/snake_game_frontend/src/App.js", "pattern": "/^const INITIAL_SNAKE = [$/", "language": "JavaScript", "kind": "constant"}, {"_type": "tag", "name": "TICK_MS", "path": "/home/kavia/workspace/code-generation/treasure-snake-game-1417-1426/snake_game_frontend/src/App.js", "pattern": "/^const TICK_MS = 140; \\/\\/ game speed (ms per tick)$/", "language": "JavaScript", "kind": "constant"}, {"_type": "tag", "name": "canvasRef", "path": "/home/kavia/workspace/code-generation/treasure-snake-game-1417-1426/snake_game_frontend/src/App.js", "pattern": "/^              ref={canvasRef}$/", "language": "JavaScript", "kind": "field", "scope": "App.ref", "scopeKind": "class"}, {"_type": "tag", "name": "drawDiamond", "path": "/home/kavia/workspace/code-generation/treasure-snake-game-1417-1426/snake_game_frontend/src/App.js", "pattern": "/^function drawDiamond(ctx, cx, cy, size) {$/", "language": "JavaScript", "kind": "function", "signature": "(ctx, cx, cy, size)"}, {"_type": "tag", "name": "gameOver", "path": "/home/kavia/workspace/code-generation/treasure-snake-game-1417-1426/snake_game_frontend/src/App.js", "pattern": "/^              aria-label={gameOver ? 'Restart game' : (isPlaying ? 'Restart game' : 'Start game'/", "language": "JavaScript", "kind": "field", "scope": "App.aria", "scopeKind": "class"}, {"_type": "tag", "name": "getRandomTreasure", "path": "/home/kavia/workspace/code-generation/treasure-snake-game-1417-1426/snake_game_frontend/src/App.js", "pattern": "/^function getRandomTreasure(snake) {$/", "language": "JavaScript", "kind": "function", "signature": "(snake)"}, {"_type": "tag", "name": "isPlaying", "path": "/home/kavia/workspace/code-generation/treasure-snake-game-1417-1426/snake_game_frontend/src/App.js", "pattern": "/^              aria-label={isPlaying ? 'Pause game' : 'Resume game'}$/", "language": "JavaScript", "kind": "field", "scope": "App.aria", "scopeKind": "class"}, {"_type": "tag", "name": "pauseResume", "path": "/home/kavia/workspace/code-generation/treasure-snake-game-1417-1426/snake_game_frontend/src/App.js", "pattern": "/^              onClick={pauseResume}$/", "language": "JavaScript", "kind": "field", "scope": "App.onClick", "scopeKind": "class"}, {"_type": "tag", "name": "pos", "path": "/home/kavia/workspace/code-generation/treasure-snake-game-1417-1426/snake_game_frontend/src/App.js", "pattern": "/^    pos = {$/", "language": "JavaScript", "kind": "class", "scope": "getRandomTreasure", "scopeKind": "class"}, {"_type": "tag", "name": "roundRect", "path": "/home/kavia/workspace/code-generation/treasure-snake-game-1417-1426/snake_game_frontend/src/App.js", "pattern": "/^function roundRect(ctx, x, y, w, h, r) {$/", "language": "JavaScript", "kind": "function", "signature": "(ctx, x, y, w, h, r)"}, {"_type": "tag", "name": "startGame", "path": "/home/kavia/workspace/code-generation/treasure-snake-game-1417-1426/snake_game_frontend/src/App.js", "pattern": "/^              onClick={startGame}$/", "language": "JavaScript", "kind": "field", "scope": "App.onClick", "scopeKind": "class"}, {"_type": "tag", "name": "updateCanvasScale", "path": "/home/kavia/workspace/code-generation/treasure-snake-game-1417-1426/snake_game_frontend/src/App.js", "pattern": "/^    function updateCanvasScale() {$/", "language": "JavaScript", "kind": "function", "signature": "()", "scope": "App", "scopeKind": "function"}, {"_type": "tag", "name": "x", "path": "/home/kavia/workspace/code-generation/treasure-snake-game-1417-1426/snake_game_frontend/src/App.js", "pattern": "/^      x: Math.floor(Math.random() * GRID_SIZE),$/", "language": "JavaScript", "kind": "property", "scope": "getRandomTreasure.pos", "scopeKind": "class"}, {"_type": "tag", "name": "x", "path": "/home/kavia/workspace/code-generation/treasure-snake-game-1417-1426/snake_game_frontend/src/App.js", "pattern": "/^const INITIAL_DIRECTION = { x: 1, y: 0 }; \\/\\/ moving right$/", "language": "JavaScript", "kind": "property", "scope": "INITIAL_DIRECTION", "scopeKind": "class"}, {"_type": "tag", "name": "y", "path": "/home/kavia/workspace/code-generation/treasure-snake-game-1417-1426/snake_game_frontend/src/App.js", "pattern": "/^      y: Math.floor(Math.random() * GRID_SIZE),$/", "language": "JavaScript", "kind": "property", "scope": "getRandomTreasure.pos", "scopeKind": "class"}, {"_type": "tag", "name": "y", "path": "/home/kavia/workspace/code-generation/treasure-snake-game-1417-1426/snake_game_frontend/src/App.js", "pattern": "/^const INITIAL_DIRECTION = { x: 1, y: 0 }; \\/\\/ moving right$/", "language": "JavaScript", "kind": "property", "scope": "INITIAL_DIRECTION", "scopeKind": "class"}], "hash": "92740cfe564c2e0663dc184bccf450e2", "format-version": 4, "code-base-name": "snake_game_frontend", "filename": "snake_game_frontend/src/App.js", "fields": [{"name": "height={GRID_SIZE * CELL_SIZE}", "scope": "App.height", "scopeKind": "class", "description": "unavailable"}, {"name": "width={GRID_SIZE * CELL_SIZE}", "scope": "App.width", "scopeKind": "class", "description": "unavailable"}, {"name": "ref={canvasRef}", "scope": "App.ref", "scopeKind": "class", "description": "unavailable"}, {"name": "aria-label={gameOver ? 'Restart game' : (isPlaying ? 'Restart game' : 'Start game'/", "scope": "App.aria", "scopeKind": "class", "description": "unavailable"}, {"name": "aria-label={isPlaying ? 'Pause game' : 'Resume game'}", "scope": "App.aria", "scopeKind": "class", "description": "unavailable"}, {"name": "onClick={pauseResume}", "scope": "App.onClick", "scopeKind": "class", "description": "unavailable"}, {"name": "onClick={startGame}", "scope": "App.onClick", "scopeKind": "class", "description": "unavailable"}, {"name": "x: Math.floor(Math.random() * GRID_SIZE),", "scope": "getRandomTreasure.pos", "scopeKind": "class", "description": "unavailable"}, {"name": "const INITIAL_DIRECTION = { x: 1, y: 0 }; \\/\\/ moving right", "scope": "INITIAL_DIRECTION", "scopeKind": "class", "description": "unavailable"}, {"name": "y: Math.floor(Math.random() * GRID_SIZE),", "scope": "getRandomTreasure.pos", "scopeKind": "class", "description": "unavailable"}]}